.travis.yml
alltests-plone.cfg
alltests-plone43.cfg
alltests-plone50.cfg
bootstrap.py
build_test.sh
buildout-zope212.cfg
buildout-zope213.cfg
buildout.cfg
setup.py
Products/__init__.py
Products.TextIndexNG3.egg-info/PKG-INFO
Products.TextIndexNG3.egg-info/SOURCES.txt
Products.TextIndexNG3.egg-info/dependency_links.txt
Products.TextIndexNG3.egg-info/entry_points.txt
Products.TextIndexNG3.egg-info/namespace_packages.txt
Products.TextIndexNG3.egg-info/not-zip-safe
Products.TextIndexNG3.egg-info/requires.txt
Products.TextIndexNG3.egg-info/top_level.txt
Products/TextIndexNG3/CHANGES.txt
Products/TextIndexNG3/INSTALL.txt
Products/TextIndexNG3/Makefile
Products/TextIndexNG3/TextIndexNG3.py
Products/TextIndexNG3/__init__.py
Products/TextIndexNG3/browser.py
Products/TextIndexNG3/configure.zcml
Products/TextIndexNG3/exportimport.py
Products/TextIndexNG3/exportimport.zcml
Products/TextIndexNG3/header.txt
Products/TextIndexNG3/version.txt
Products/TextIndexNG3/Extensions/Install.py
Products/TextIndexNG3/adapters/README.txt
Products/TextIndexNG3/adapters/__init__.py
Products/TextIndexNG3/adapters/cmf_adapters.py
Products/TextIndexNG3/adapters/configure.zcml
Products/TextIndexNG3/adapters/plone_adapters.py
Products/TextIndexNG3/doc/LICENSE.txt
Products/TextIndexNG3/doc/README.txt
Products/TextIndexNG3/doc/ZPL.txt
Products/TextIndexNG3/i18n/TextIndexNG3-de.po
Products/TextIndexNG3/i18n/TextIndexNG3.pot
Products/TextIndexNG3/interfaces/__init__.py
Products/TextIndexNG3/interfaces/textindexng.py
Products/TextIndexNG3/profiles/default/catalog.xml
Products/TextIndexNG3/profiles/default/metadata.xml
Products/TextIndexNG3/pt/adapters.pt
Products/TextIndexNG3/pt/add.pt
Products/TextIndexNG3/pt/converters.pt
Products/TextIndexNG3/pt/documentsforword.pt
Products/TextIndexNG3/pt/index.gif
Products/TextIndexNG3/pt/manage.pt
Products/TextIndexNG3/pt/queryform.pt
Products/TextIndexNG3/pt/thesaurus.pt
Products/TextIndexNG3/pt/txng_footer.pt
Products/TextIndexNG3/pt/vocabulary.pt
Products/TextIndexNG3/skins/textindexng3/index.gif
Products/TextIndexNG3/skins/textindexng3/txng_convert_indexes.py
Products/TextIndexNG3/skins/textindexng3/txng_maintenance.pt
Products/TextIndexNG3/tests/__init__.py
Products/TextIndexNG3/tests/testAdapters.py
Products/TextIndexNG3/tests/testExportImport.py
Products/TextIndexNG3/tests/testPlone.py
