Metadata-Version: 1.0
Name: Products.TextIndexNG3
Version: 3.4.12
Summary: Pluggable fulltext indexing solution for Zope and Plone
Home-page: https://pypi.python.org/pypi/Products.TextIndexNG3
Author: Andreas Jung
Author-email: info@zopyx.com
License: ZPL (see LICENSE.txt)
Keywords: Zope2 Zope3 fulltext indexing
Platform: UNKNOWN
Classifier: Programming Language :: Python
